elm_doc/__init__.py
elm_doc/assets/assets.tar.gz
elm_doc/cli.py
elm_doc/elm_codeshift.py
elm_doc/elm_parser/__init__.py
elm_doc/elm_parser/lines.py
elm_doc/elm_parser/ports.py
elm_doc/elm_platform.py
elm_doc/elm_project.py
elm_doc/loader.py
elm_doc/run_config.py
elm_doc/tasks/__init__.py
elm_doc/tasks/assets.py
elm_doc/tasks/catalog.py
elm_doc/tasks/html.py
elm_doc/tasks/package.py
elm_doc/tasks/project.py
elm_doc/utils.py
elm_doc-1.0.0.dist-info/entry_points.txt
elm_doc-1.0.0.dist-info/LICENSE
elm_doc-1.0.0.dist-info/WHEEL
elm_doc-1.0.0.dist-info/METADATA
elm_doc-1.0.0.dist-info/RECORD
