Metadata-Version: 2.1
Name: elm-doc
Version: 1.0.0
Summary: Generate static documentation for your Elm application
Home-page: https://github.com/ento/elm-doc
License: BSD-3-Clause
Author: ento
Author-email: ento+github@i.pearlwaffles.xyz
Requires-Python: >=3.5,<4.0
Classifier: Development Status :: 5 - Production/Stable
Classifier: Environment :: Console
Classifier: Intended Audience :: Developers
Classifier: License :: OSI Approved :: BSD License
Classifier: Programming Language :: Python :: 3
Classifier: Programming Language :: Python :: 3.5
Classifier: Programming Language :: Python :: 3.6
Classifier: Programming Language :: Python :: 3.7
Classifier: Programming Language :: Python :: 3.8
Classifier: Programming Language :: Python :: 3.9
Classifier: Topic :: Software Development :: Documentation
Requires-Dist: attrs (>=19.3.0,<20.0.0)
Requires-Dist: cachecontrol (>=0.12.6,<0.13.0)
Requires-Dist: click (>=7.1.2,<8.0.0)
Requires-Dist: doit (>=0.32.0,<0.33.0)
Requires-Dist: parsy (>=1.3.0,<2.0.0)
Requires-Dist: requests (>=2.24.0,<3.0.0)
Requires-Dist: retrying (>=1.3.3,<2.0.0)
Project-URL: Repository, https://github.com/ento/elm-doc
